{
  "timestamp": "2026-05-02T11:19:19.165338+00:00",
  "running": true,
  "scan_count": 4139,
  "positions_count": 1,
  "positions": [
    {
      "symbol": "NEARUSDC",
      "direction": "LONG",
      "strategy": "mean_reversion",
      "entry_price": 1.288,
      "qty": 644.1,
      "position_size": 828.3181520975,
      "open_time": 1777720505.5429862,
      "tp_pct": 0.25,
      "sl_pct": -0.8,
      "trailing_pct": 0.08,
      "trailing_active": false
    }
  ],
  "daily_pnl": -0.3109,
  "capital": 3313.27260839,
  "drawdown_pct": 0.0,
  "circuit_breaker": false,
  "consecutive_losses": 1,
  "daily_pnl_calculated": true,
  "daily_pnl_date": "2026-05-02",
  "today_trades_count": 2
}