{
  "bot": {
    "balance": 565.14,
    "positions": [],
    "last_scan": "2026-04-14T07:45:01.539451",
    "rsi_data": {
      "SOLUSDC": {
        "rsi": 50.0,
        "signal": "none"
      },
      "ETHUSDC": {
        "rsi": 43.0,
        "signal": "none"
      },
      "BTCUSDC": {
        "rsi": 30.5,
        "signal": "none"
      }
    },
    "status": "online"
  },
  "trades": [
    {
      "timestamp": "2026-04-14T06:49:20",
      "symbol": "PF_SOLUSD",
      "side": "LONG",
      "entry_price": 85.98,
      "exit_price": 85.71,
      "size": 0.92,
      "pnl_usd": -0.2484,
      "pnl_pct": -0.314,
      "duration": "1804",
      "exit_reason": "TIMEOUT"
    },
    {
      "timestamp": "2026-04-14T06:16:46",
      "symbol": "PF_SOLUSD",
      "side": "LONG",
      "entry_price": 85.96,
      "exit_price": 85.97,
      "size": 0.92,
      "pnl_usd": 0.0092,
      "pnl_pct": 0.0116,
      "duration": "909",
      "exit_reason": "SMART_TIMEOUT_900S"
    },
    {
      "timestamp": "2026-04-14T05:51:50",
      "symbol": "PF_NEARUSD",
      "side": "LONG",
      "entry_price": 1.4073,
      "exit_price": 1.4079,
      "size": 57.09,
      "pnl_usd": 0.0343,
      "pnl_pct": 0.0426,
      "duration": "841",
      "exit_reason": "TRAILING_STOP"
    },
    {
      "timestamp": "2026-04-14T05:18:37",
      "symbol": "PF_NEARUSD",
      "side": "LONG",
      "entry_price": 1.4075,
      "exit_price": 1.4073,
      "size": 57.08,
      "pnl_usd": -0.0114,
      "pnl_pct": -0.0142,
      "duration": "801",
      "exit_reason": "TRAILING_STOP"
    },
    {
      "timestamp": "2026-04-14T03:12:29",
      "symbol": "PF_SOLUSD",
      "side": "LONG",
      "entry_price": 86.04,
      "exit_price": 86.06,
      "size": 0.93,
      "pnl_usd": 0.0186,
      "pnl_pct": 0.0232,
      "duration": "1556",
      "exit_reason": "SMART_TIMEOUT_900S"
    },
    {
      "timestamp": "2026-04-14T02:36:59",
      "symbol": "PF_SOLUSD",
      "side": "LONG",
      "entry_price": 86.14,
      "exit_price": 86.4,
      "size": 0.93,
      "pnl_usd": 0.2418,
      "pnl_pct": 0.3018,
      "duration": "113",
      "exit_reason": "TAKE_PROFIT"
    },
    {
      "timestamp": "2026-04-13T22:37:57",
      "symbol": "PF_NEARUSD",
      "side": "LONG",
      "entry_price": 1.3927,
      "exit_price": 1.3933,
      "size": 57.68,
      "pnl_usd": 0.0346,
      "pnl_pct": 0.0431,
      "duration": "904",
      "exit_reason": "SMART_TIMEOUT_900S"
    },
    {
      "timestamp": "2026-04-13T22:22:40",
      "symbol": "PF_NEARUSD",
      "side": "LONG",
      "entry_price": 1.3925,
      "exit_price": 1.3927,
      "size": 57.68,
      "pnl_usd": 0.0115,
      "pnl_pct": 0.0144,
      "duration": "157",
      "exit_reason": "TRAILING_STOP"
    },
    {
      "timestamp": "2026-04-13T20:33:04",
      "symbol": "PF_SOLUSD",
      "side": "LONG",
      "entry_price": 82.81,
      "exit_price": 83.04,
      "size": 0.97,
      "pnl_usd": 0.2231,
      "pnl_pct": 0.2777,
      "duration": "521",
      "exit_reason": "TAKE_PROFIT"
    },
    {
      "timestamp": "2026-04-13T17:58:12",
      "symbol": "PF_SOLUSD",
      "side": "LONG",
      "entry_price": 82.52,
      "exit_price": 82.72,
      "size": 0.97,
      "pnl_usd": 0.194,
      "pnl_pct": 0.2424,
      "duration": "541",
      "exit_reason": "TAKE_PROFIT"
    }
  ],
  "summary": {
    "balance": 565.14,
    "positions_count": 0,
    "open_positions_value": 0,
    "daily_pnl": 0.0441,
    "total_trades": 40,
    "last_updated": "2026-04-14T07:45:01.540836"
  }
}